src/vault/vault.sv
module vault #(
    parameter int NUM_WORDS = 16  // 16 palabras por defecto
  )(input  logic        CLK,
    input  logic        RST,
    input  logic [31:0] A,    // 32-bit Address from ALUOut
    input  logic [3:0]  WE,   // Write Enable (Byte-strobe)
    input  logic [3:0]  ASM,  // Addressing Selection Mode
    // Data signals
    input  logic [31:0] WD,   // Write Data from RD2
    output logic [31:0] RD);    // Read Data (MemOut)


    // Calculo de los bits de direccionamiento para indexar el array
    localparam int ADDR_WIDTH = $clog2(NUM_WORDS);

    // --- Memory Storage ---
    // [31:0] is the PACKED dimension: defines the 32-bit width of each word (MSB to LSB).
    // [0:NUM_WORDS-1] is the UNPACKED dimension: defines the addressable range.
    // We use [0:N] instead of [N:0] so that the first line of the .hex file 
    // correctly maps to the lowest address (index 0) during $readmemh.
    logic [31:0] RAM [0:NUM_WORDS-1];

    // --- Address Mapping ---
    // Extract the word index using the calculated width
    // We still ignore A[1:0] for word alignment
    logic [ADDR_WIDTH-1:0] word_idx;
    assign word_idx = A[ADDR_WIDTH+1:2];

    // Byte selection within the word
    logic [1:0] byte_offset;
    assign byte_offset = A[1:0];

    // --- Initialization ---
    initial begin
        for (int i = 0; i < NUM_WORDS; i++) begin
            RAM[i] = 32'h0;
        end
        $readmemh("./src/memories/vault_mem.hex", RAM);
    end

    // --- Synchronous Write (Store) ---
    always_ff @(posedge CLK) begin
        if (RST) begin
            // Reset logic
        end else begin
            if (WE[0]) RAM[word_idx][7:0]   <= WD[7:0];
            if (WE[1]) RAM[word_idx][15:8]  <= WD[15:8];
            if (WE[2]) RAM[word_idx][23:16] <= WD[23:16];
            if (WE[3]) RAM[word_idx][31:24] <= WD[31:24];
        end
    end

    // --- Asynchronous Read (Load) ---
    logic [31:0] raw_word;
    assign raw_word = RAM[word_idx];

    always_comb begin
        case(ASM)
            4'b0000: RD = raw_word; // LW
            
            4'b0001: begin // LB / LBU selection
                case(byte_offset)
                    2'b00: RD = {24'b0, raw_word[7:0]};
                    2'b01: RD = {24'b0, raw_word[15:8]};
                    2'b10: RD = {24'b0, raw_word[23:16]};
                    2'b11: RD = {24'b0, raw_word[31:24]};
                endcase
            end
            
            4'b0010: begin // LH / LHU selection
                case(byte_offset[1])
                    1'b0: RD = {16'b0, raw_word[15:0]};
                    1'b1: RD = {16'b0, raw_word[31:16]};
                endcase
            end

            default: RD = raw_word;
        endcase
    end

endmodule

src/vault/tests/vault_tb.sv
`timescale 1ns/1ps

module vault_tb;

    logic        CLK, RST;
    logic [31:0] A, WD, RD;
    logic [3:0]  WE, ASM;

    vault #(.NUM_WORDS(16)) DUT (.CLK(CLK), .RST(RST),
                                  .A(A), .WE(WE), .ASM(ASM),
                                  .WD(WD), .RD(RD));

    // Clock 10ns
    always #5 CLK = ~CLK;

    task automatic check(input string name, input logic [31:0] exp);
        #1;
        if (RD === exp)
            $display("[PASS] %s | RD=%h", name, RD);
        else
            $display("[FAIL] %s | got=%h  exp=%h", name, RD, exp);
    endtask

    initial begin
        $dumpfile("vault_tb.vcd");   // nombre del archivo
        $dumpvars(0, vault_tb);         // qué señales guardar
        CLK = 0; RST = 1; WE = 4'b0000;
        A = 0; WD = 0; ASM = 4'b0000;
        @(posedge CLK); #1;
        RST = 0;

        // -----------------------------------------------
        // LW (ASM=0000) — leer palabras completas
        // -----------------------------------------------
        $display("--- LW ---");
        ASM = 4'b0000;

        A = 32'h00000000; check("LW RAM[0]",  32'hAABBCCDD);
        A = 32'h00000004; check("LW RAM[1]",  32'h0000000A);
        A = 32'h00000008; check("LW RAM[2]",  32'hCAFEBABE);
        A = 32'h0000003C; check("LW RAM[15]", 32'h0000000D);

        // -----------------------------------------------
        // LB (ASM=0001) — leer byte por offset
        // -----------------------------------------------
        $display("--- LB ---");
        ASM = 4'b0001;

        // RAM[0] = 0xAABBCCDD
        A = 32'h00000000; check("LB RAM[0] byte0", 32'h000000DD); // [7:0]
        A = 32'h00000001; check("LB RAM[0] byte1", 32'h000000CC); // [15:8]
        A = 32'h00000002; check("LB RAM[0] byte2", 32'h000000BB); // [23:16]
        A = 32'h00000003; check("LB RAM[0] byte3", 32'h000000AA); // [31:24]

        // -----------------------------------------------
        // LH (ASM=0010) — leer halfword por offset
        // -----------------------------------------------
        $display("--- LH ---");
        ASM = 4'b0010;

        // LH — RAM[0] = 0xAABBCCDD
        A = 32'h00000000; check("LH RAM[0] low",  32'h0000CCDD); // [15:0]
        A = 32'h00000002; check("LH RAM[0] high", 32'h0000AABB); // [31:16]

        // -----------------------------------------------
        // SW — escribir y leer de vuelta
        // -----------------------------------------------
        $display("--- SW ---");
        ASM = 4'b0000;

        // Escribir 0x12345678 en RAM[5] (A=0x14)
        A = 32'h00000014; WD = 32'h12345678; WE = 4'b1111;
        @(posedge CLK); #1;
        WE = 4'b0000;
        check("SW RAM[5] full word", 32'h12345678);

        // Escribir solo byte bajo en RAM[6] (A=0x18)
        A = 32'h00000018; WD = 32'hAABBCCDD; WE = 4'b0001;
        @(posedge CLK); #1;
        WE = 4'b0000;
        ASM = 4'b0001; A = 32'h00000018;
        check("SB RAM[6] byte0 = DD", 32'h000000DD);

        // --- 6. GUARDAR RESULTADOS ---
        $display("\n[SISTEMA] Guardando volcado de memoria final...");
        // Asegúrate de que la carpeta ./src/output/ exista físicamente
        $writememh("./src/output/vault_mod.hex", DUT.RAM);
        
        $display("[SISTEMA] Archivo generado exitosamente.");

        $display("--- FIN ---");
        $finish;
    end

endmodule

vault_tb.vcd
$date
	Sat Apr 25 15:15:30 2026
$end
$version
	Icarus Verilog
$end
$timescale
	1ps
$end
$scope module vault_tb $end
$var wire 32 ! RD [31:0] $end
$var reg 32 " A [31:0] $end
$var reg 4 # ASM [3:0] $end
$var reg 1 $ CLK $end
$var reg 1 % RST $end
$var reg 32 & WD [31:0] $end
$var reg 4 ' WE [3:0] $end
$scope module DUT $end
$var wire 32 ( A [31:0] $end
$var wire 4 ) ASM [3:0] $end
$var wire 1 $ CLK $end
$var wire 1 % RST $end
$var wire 32 * WD [31:0] $end
$var wire 4 + WE [3:0] $end
$var wire 32 , raw_word [31:0] $end
$var wire 4 - word_idx [3:0] $end
$var wire 2 . byte_offset [1:0] $end
$var parameter 32 / ADDR_WIDTH $end
$var parameter 32 0 NUM_WORDS $end
$var reg 32 1 RD [31:0] $end
$scope begin $ivl_for_loop0 $end
$var integer 32 2 i [31:0] $end
$upscope $end
$upscope $end
$scope task check $end
$upscope $end
$upscope $end
$enddefinitions $end
$comment Show the parameter values. $end
$dumpall
b10000 0
b100 /
$end
#0
$dumpvars
b10000 2
b10101010101110111100110011011101 1
b0 .
b0 -
b10101010101110111100110011011101 ,
b0 +
b0 *
b0 )
b0 (
b0 '
b0 &
1%
0$
b0 #
b0 "
b10101010101110111100110011011101 !
$end
#5000
1$
#6000
0%
#7000
b1010 !
b1010 1
b1010 ,
b1 -
b100 "
b100 (
#8000
b11001010111111101011101010111110 !
b11001010111111101011101010111110 1
b11001010111111101011101010111110 ,
b10 -
b1000 "
b1000 (
#9000
b1101 !
b1101 1
b1101 ,
b1111 -
b111100 "
b111100 (
#10000
b11011101 !
b11011101 1
b10101010101110111100110011011101 ,
b0 -
b0 "
b0 (
b1 #
b1 )
0$
#11000
b11001100 !
b11001100 1
b1 .
b1 "
b1 (
#12000
b10111011 !
b10111011 1
b10 .
b10 "
b10 (
#13000
b10101010 !
b10101010 1
b11 .
b11 "
b11 (
#14000
b0 .
b1100110011011101 !
b1100110011011101 1
b0 "
b0 (
b10 #
b10 )
#15000
b1010101010111011 !
b1010101010111011 1
b10 .
b10 "
b10 (
1$
#16000
b11 ,
b101 -
b0 .
b11 !
b11 1
b1111 '
b1111 +
b10010001101000101011001111000 &
b10010001101000101011001111000 *
b10100 "
b10100 (
b0 #
b0 )
#20000
0$
#25000
b10010001101000101011001111000 !
b10010001101000101011001111000 1
b10010001101000101011001111000 ,
1$
#26000
b0 '
b0 +
#27000
b100 !
b100 1
b100 ,
b110 -
b1 '
b1 +
b10101010101110111100110011011101 &
b10101010101110111100110011011101 *
b11000 "
b11000 (
#30000
0$
#35000
b11011101 !
b11011101 1
b11011101 ,
1$
#36000
b1 #
b1 )
b0 '
b0 +
