src/datamem/data_memory.sv
module data_memory #(
    parameter int MEM_SIZE_KB = 64  // Default size: 64 KB
)(
    // Global signals
    input  logic        CLK,
    input  logic        RST,
    // Control signals
    input  logic [31:0] A,    // 32-bit Address from ALUOut
    input  logic [3:0]  WE,   // Write Enable (Byte-strobe)
    input  logic [3:0]  ASM,  // Addressing Selection Mode
    // Data signals
    input  logic [31:0] WD,   // Write Data from RD2
    output logic [31:0] RD    // Read Data (MemOut)
);

    // --- Dynamic Parameter Calculation ---
    // 1. Calculate total words: (KB * 1024 bytes) / 4 bytes per word
    localparam int NUM_WORDS = (MEM_SIZE_KB * 1024) / 4;
    
    // 2. Calculate address bits needed for the array index: log2(NUM_WORDS)
    // $clog2 is a system function that computes the ceiling of the log base 2
    localparam int ADDR_WIDTH = $clog2(NUM_WORDS);

    // --- Memory Storage ---
    // [31:0] is the PACKED dimension: defines the 32-bit width of each word (MSB to LSB).
    // [0:NUM_WORDS-1] is the UNPACKED dimension: defines the addressable range.
    // We use [0:N] instead of [N:0] so that the first line of the .hex file 
    // correctly maps to the lowest address (index 0) during $readmemh.
    logic [31:0] RAM [0:NUM_WORDS-1];

    // --- Address Mapping ---
    // Extract the word index using the calculated width
    // We still ignore A[1:0] for word alignment
    logic [ADDR_WIDTH-1:0] word_idx;
    assign word_idx = A[ADDR_WIDTH+1:2];

    // Byte selection within the word
    logic [1:0] byte_offset;
    assign byte_offset = A[1:0];

    // --- Initialization ---
    initial begin
        for (int i = 0; i < NUM_WORDS-1; i++) begin
            RAM[i] = 32'h0;
        end
        $readmemh("./src/datamem/data_mem.hex", RAM);
    end

    // --- Synchronous Write (Store) ---
    always_ff @(posedge CLK) begin
        if (RST) begin
            // Reset logic
        end else begin
            if (WE[0]) RAM[word_idx][7:0]   <= WD[7:0];
            if (WE[1]) RAM[word_idx][15:8]  <= WD[15:8];
            if (WE[2]) RAM[word_idx][23:16] <= WD[23:16];
            if (WE[3]) RAM[word_idx][31:24] <= WD[31:24];
        end
    end

    // --- Asynchronous Read (Load) ---
    logic [31:0] raw_word;
    assign raw_word = RAM[word_idx];

    always_comb begin
        case(ASM)
            4'b0000: RD = raw_word; // LW
            
            4'b0001: begin // LB / LBU selection
                case(byte_offset)
                    2'b00: RD = {24'b0, raw_word[7:0]};
                    2'b01: RD = {24'b0, raw_word[15:8]};
                    2'b10: RD = {24'b0, raw_word[23:16]};
                    2'b11: RD = {24'b0, raw_word[31:24]};
                endcase
            end
            
            4'b0010: begin // LH / LHU selection
                case(byte_offset[1])
                    1'b0: RD = {16'b0, raw_word[15:0]};
                    1'b1: RD = {16'b0, raw_word[31:16]};
                endcase
            end

            default: RD = raw_word;
        endcase
    end

endmodule

src/datamem/tests/data_memory_tb.sv
`timescale 1ns/1ps

module data_memory_tb();

    parameter MEM_SIZE_KB = 64;
    parameter CLK_PERIOD = 10;

    logic        CLK, RST;
    logic [31:0] A, WD, RD;
    logic [3:0]  WE, ASM;

    data_memory #(.MEM_SIZE_KB(MEM_SIZE_KB)) uut (
        .CLK(CLK), .RST(RST), .A(A), .WE(WE), .ASM(ASM), .WD(WD), .RD(RD)
    );

    always #(CLK_PERIOD/2) CLK = ~CLK;

    initial begin
        // --- 1. Inicialización ---
        CLK = 0; RST = 1; A = 0; WE = 0; ASM = 0; WD = 0;
        #(CLK_PERIOD*5); RST = 0; #(CLK_PERIOD*2);

        $display("\n=== LABORATORIO DE MEMORIA: TEST DE ALINEACION ===");
        
        // --- 2. PRUEBA DE CARGA DE PALABRA (LW) ---
        // Asumiendo que cargaste 04030201 en la dirección 0x0
        A = 32'h00000000; ASM = 4'b0000; 
        #(CLK_PERIOD);
        $display("[LW]  Dir 0x00: %h (Esperado: 04030201)", RD);

        // --- 3. PRUEBA DE BYTES (LB) EN CADENA ---
        $display("\n--- Test de desplazamiento de Bytes (LB) ---");
        for (int i = 0; i < 4; i++) begin
            A = 32'h00000000 + i;
            ASM = 4'b0001; // Modo Byte
            #(CLK_PERIOD);
            $display("[LB]  Dir 0x%0h: %h (Esperado: %02h)", A, RD, i+1);
        end

        // --- 4. PRUEBA DE MEDIAS PALABRAS (LH) ---
        $display("\n--- Test de Medias Palabras (LH) ---");
        // Parte baja (Bytes 0 y 1)
        A = 32'h00000000; ASM = 4'b0010; 
        #(CLK_PERIOD);
        $display("[LH]  Dir 0x00: %h (Esperado: 00000201)", RD);
        
        // Parte alta (Bytes 2 y 3)
        A = 32'h00000002; ASM = 4'b0010; 
        #(CLK_PERIOD);
        $display("[LH]  Dir 0x02: %h (Esperado: 00000403)", RD);

        // --- 5. TEST DE "VANDALISMO" CONTROLADO ---
        $display("\n--- Escribiendo 0xFF en el Byte 2 de 0x00 ---");
        // Queremos que 04030201 pase a ser 04FF0201
        EscribirUnByte(32'h00000002, 8'hFF, 4'b0100); 
        
        A = 32'h00000000; ASM = 4'b0000; // Volver a leer palabra completa
        #(CLK_PERIOD);
        $display("[LW]  Resultado Final: %h (Esperado: 04ff0201)", RD);

        #(CLK_PERIOD*5);

        // --- 6. GUARDAR RESULTADOS ---
        $display("\n[SISTEMA] Guardando volcado de memoria final...");
        // Asegúrate de que la carpeta ./src/output/ exista físicamente
        $writememh("./output/ram_exit.hex", uut.RAM);
        
        $display("[SISTEMA] Archivo generado exitosamente.");

        $finish;
    end

    // Tarea de escritura reutilizada
    task EscribirUnByte(input [31:0] addr, input [7:0] data, input [3:0] byte_en);
        begin
            @(posedge CLK); #2;
            A = addr; WE = byte_en; WD = {data, data, data, data};
            @(posedge CLK); #2;
            WE = 0;
        end
    endtask

endmodule

src/output/wave.vcd
$date
	Fri Apr 24 20:23:06 2026
$end
$version
	Icarus Verilog
$end
$timescale
	1ps
$end
$scope module data_memory_tb $end
$var wire 32 ! RD [31:0] $end
$var parameter 32 " CLK_PERIOD $end
$var parameter 32 # MEM_SIZE_KB $end
$var reg 32 $ A [31:0] $end
$var reg 4 % ASM [3:0] $end
$var reg 1 & CLK $end
$var reg 1 ' RST $end
$var reg 32 ( WD [31:0] $end
$var reg 4 ) WE [3:0] $end
$scope module uut $end
$var wire 32 * A [31:0] $end
$var wire 4 + ASM [3:0] $end
$var wire 1 & CLK $end
$var wire 1 ' RST $end
$var wire 32 , WD [31:0] $end
$var wire 4 - WE [3:0] $end
$var wire 32 . raw_word [31:0] $end
$var wire 14 / word_idx [13:0] $end
$var wire 2 0 byte_offset [1:0] $end
$var parameter 32 1 ADDR_WIDTH $end
$var parameter 32 2 MEM_SIZE_KB $end
$var parameter 32 3 NUM_WORDS $end
$var reg 32 4 RD [31:0] $end
$scope begin $ivl_for_loop0 $end
$var integer 32 5 i [31:0] $end
$upscope $end
$upscope $end
$scope task EscribirUnByte $end
$var reg 32 6 addr [31:0] $end
$var reg 4 7 byte_en [3:0] $end
$var reg 8 8 data [7:0] $end
$upscope $end
$scope task LeerUnByte $end
$var reg 32 9 addr [31:0] $end
$upscope $end
$upscope $end
$enddefinitions $end
$comment Show the parameter values. $end
$dumpall
b100000000000000 3
b1000000 2
b1110 1
b1000000 #
b1010 "
$end
#0
$dumpvars
bx 9
bx 8
bx 7
bx 6
b11111111111111 5
b1000111010011100101000010001001 4
b0 0
b0 /
b1000111010011100101000010001001 .
b0 -
b0 ,
b0 +
b0 *
b0 )
b0 (
1'
0&
b0 %
b0 $
b1000111010011100101000010001001 !
$end
#5000
1&
#10000
0&
#15000
1&
#20000
0&
#25000
1&
#30000
0&
#35000
1&
#40000
0&
#45000
1&
#50000
0&
0'
#55000
1&
#60000
0&
#65000
1&
#70000
0&
b10 7
b11111111 8
b1000001 6
#75000
1&
#77000
b11111011110111101000101100000111 !
b11111011110111101000101100000111 4
b11111011110111101000101100000111 .
b10000 /
b1 0
b11111111111111111111111111111111 (
b11111111111111111111111111111111 ,
b10 )
b10 -
b1000001 $
b1000001 *
#80000
0&
#85000
b11111011110111101111111100000111 !
b11111011110111101111111100000111 4
b11111011110111101111111100000111 .
1&
#87000
b1000001 9
b0 )
b0 -
#90000
0&
#95000
1&
#97000
b11111111 !
b11111111 4
b1 %
b1 +
#100000
0&
#105000
1&
#107000
b11111011110111101111111100000111 !
b11111011110111101111111100000111 4
b1000 7
b10000 8
b1100011 6
b0 %
b0 +
#110000
0&
#115000
1&
#117000
b1010111001110101100110001001011 !
b1010111001110101100110001001011 4
b1010111001110101100110001001011 .
b11000 /
b11 0
b10000000100000001000000010000 (
b10000000100000001000000010000 ,
b1000 )
b1000 -
b1100011 $
b1100011 *
#120000
0&
#125000
b10000001110101100110001001011 !
b10000001110101100110001001011 4
b10000001110101100110001001011 .
1&
#127000
b1100011 9
b0 )
b0 -
#130000
0&
#135000
1&
#137000
b10000 !
b10000 4
b1 %
b1 +
#140000
0&
#145000
1&
#147000
b10000001110101100110001001011 !
b10000001110101100110001001011 4
b1 7
b10101011 8
b10000100 6
b0 %
b0 +
#150000
0&
#155000
1&
#157000
b10110010110110010010001001011 !
b10110010110110010010001001011 4
b10110010110110010010001001011 .
b100001 /
b0 0
b10101011101010111010101110101011 (
b10101011101010111010101110101011 ,
b1 )
b1 -
b10000100 $
b10000100 *
#160000
0&
#165000
b10110010110110010010010101011 !
b10110010110110010010010101011 4
b10110010110110010010010101011 .
1&
#167000
b10000100 9
b0 )
b0 -
#170000
0&
#175000
1&
#177000
b10101011 !
b10101011 4
b1 %
b1 +
#180000
0&
#185000
1&
#187000
b10110010110110010010010101011 !
b10110010110110010010010101011 4
b0 %
b0 +
